setup.cfg
setup.py
liquid4m/__init__.py
liquid4m/dialects.py
liquid4m/elements.py
liquid4m/exceptions.py
liquid4m/form.py
liquid4m/state.py
liquid4m/tests.py
liquid4m/validators.py
liquid4m/widgets.py
liquid4m.egg-info/PKG-INFO
liquid4m.egg-info/SOURCES.txt
liquid4m.egg-info/dependency_links.txt
liquid4m.egg-info/not-zip-safe
liquid4m.egg-info/requires.txt
liquid4m.egg-info/top_level.txt
liquid4m/fields/__init__.py
liquid4m/fields/options.py
liquid4m/fields/types.py
liquid4m/fields/validators.py
liquid4m/fieldsets/__init__.py
liquid4m/fieldsets/validators.py