Metadata-Version: 1.0
Name: liquid4m
Version: 0.1dev
Summary: Liquid form management for dummies
Home-page: UNKNOWN
Author: Bence Faludi
Author-email: b.faludi@mito.hu
License: GPL
Platform: UNKNOWN
